{
  "code": 0,
  "msg": "",
  "count": 100,
  "data": [
    {
      "zizeeng": 1,
      "cname": "北京柯蓝科技有限公司",
      "cpeople":"刘海海",
      "teacher":"张三",
      "time":"2019-11-02",
      "address":"科技楼11层"
    }, {
       "zizeeng": 1,
      "cname": "北京柯蓝科技有限公司",
      "cpeople":"刘海海",
      "teacher":"张三",
      "time":"2019-11-02",
      "address":"科技楼11层"
    }, {
       "zizeeng": 1,
      "cname": "北京柯蓝科技有限公司",
      "cpeople":"刘海海",
      "teacher":"张三",
      "time":"2019-11-02",
      "address":"科技楼11层"
    }, {
       "zizeeng": 1,
      "cname": "北京柯蓝科技有限公司",
      "cpeople":"刘海海",
      "teacher":"张三",
      "time":"2019-11-02",
      "address":"科技楼11层"
    }, {
       "zizeeng": 1,
      "cname": "北京柯蓝科技有限公司",
      "cpeople":"刘海海",
      "teacher":"张三",
      "time":"2019-11-02",
      "address":"科技楼11层"
    }, {
       "zizeeng": 1,
      "cname": "北京柯蓝科技有限公司",
      "cpeople":"刘海海",
      "teacher":"张三",
      "time":"2019-11-02",
      "address":"科技楼11层"
    }
  ]
}